cmder/__init__.py
cmder/command.py
cmder/config.py
cmder/console.py
cmder/data.py
cmder/decorator.py
cmder/exception.py
cmder/logging.py
cmder/main.py
cmder/menu.py
cmder/output.py
cmder/parse.py
cmder/unit.py
cmder/variable.py
cmder_elinpf-2.2.3.data/scripts/cmder
cmder_elinpf-2.2.3.dist-info/LICENSE
cmder_elinpf-2.2.3.dist-info/METADATA
cmder_elinpf-2.2.3.dist-info/WHEEL
cmder_elinpf-2.2.3.dist-info/top_level.txt
cmder_elinpf-2.2.3.dist-info/RECORD
