Metadata-Version: 2.1
Name: cmder-elinpf
Version: 2.2.3
Summary: Simple CLI tool for the generation hack commands.
Home-page: https://github.com/Elinpf/cmder
Author: Elin
License: UNKNOWN
Platform: UNKNOWN
Classifier: Environment :: Console
Classifier: License :: OSI Approved :: GNU General Public License v3 (GPLv3)
Classifier: Operating System :: POSIX :: Linux
Classifier: Programming Language :: Python :: 3
Classifier: Topic :: Security
Requires-Python: >=3.6
Requires-Dist: colorama
Requires-Dist: simple-term-menu
Requires-Dist: rich-typer (==0.1.5)
